folders2json/__init__.py
folders2json/__main__.py
folders2json/folders2json.py
folders2json/functions.py
folders2json-1.1.2.dist-info/METADATA
folders2json-1.1.2.dist-info/WHEEL
folders2json-1.1.2.dist-info/entry_points.txt
folders2json-1.1.2.dist-info/top_level.txt
folders2json-1.1.2.dist-info/RECORD
